reservedseating.py
mindpowered_reservedseating/ReservedSeating.py
mindpowered_reservedseating/__init__.py
mindpowered_reservedseating-0.0.5.dist-info/LICENSE.txt
mindpowered_reservedseating-0.0.5.dist-info/METADATA
mindpowered_reservedseating-0.0.5.dist-info/WHEEL
mindpowered_reservedseating-0.0.5.dist-info/top_level.txt
mindpowered_reservedseating-0.0.5.dist-info/RECORD
